{"name":"root","children":[{"name":"note","children":[{"name":"2020-2-28","children":[{"name":"2K","children":[{"file":"8642c4d86b-プレミアム会員｜note.png","size":61209}]},{"name":"4K","children":[{"file":"8642c4d86b-プレミアム会員｜note.png","size":602481}]},{"name":"iPad_Pro","children":[{"file":"8642c4d86b-プレミアム会員｜note.png","size":602481}]},{"name":"iPhone_X","children":[{"file":"8642c4d86b-プレミアム会員｜note.png","size":602481}]}]}]},{"name":"slack","children":[{"name":"2020-2-28","children":[{"name":"2K","children":[{"file":"0ce1194b35-コラボレーションのためのソフトウェアSlack.png","size":2786801},{"file":"0ce1194b35-機能Slack.png","size":1208426},{"file":"981c26e1aa-その仕事、Slackで。Slack.png","size":4144038}]},{"name":"4K","children":[{"file":"0ce1194b35-コラボレーションのためのソフトウェアSlack.png","size":2782298},{"file":"0ce1194b35-機能Slack.png","size":2802571},{"file":"981c26e1aa-その仕事、Slackで。Slack.png","size":4144038}]},{"name":"iPad_Pro","children":[{"file":"0ce1194b35-コラボレーションのためのソフトウェアSlack.png","size":2810769},{"file":"0ce1194b35-機能Slack.png","size":2861141},{"file":"981c26e1aa-その仕事、Slackで。Slack.png","size":4144038}]},{"name":"iPhone_X","children":[{"file":"0ce1194b35-コラボレーションのためのソフトウェアSlack.png","size":2846794},{"file":"981c26e1aa-その仕事、Slackで。Slack.png","size":4144038}]}]}]}]}